orurhandler
