Metadata-Version: 2.1
Name: orurhandler
Version: 0.0.2
Summary: User Management with AWS Cognito.
Home-page: https://github.com/leonardomra/orurhandler
Author: Leonardo de Araújo
Author-email: dearaujo@uni-bremen.de
License: UNKNOWN
Platform: UNKNOWN
Classifier: Programming Language :: Python :: 3
Classifier: License :: OSI Approved :: MIT License
Classifier: Operating System :: OS Independent
Requires-Python: >=3.6
